analysts_tool_share/__init__.py
analysts_tool_share/hello.py
analysts_tool_share-0.0.1.dist-info/LICENSE
analysts_tool_share-0.0.1.dist-info/METADATA
analysts_tool_share-0.0.1.dist-info/WHEEL
analysts_tool_share-0.0.1.dist-info/top_level.txt
analysts_tool_share-0.0.1.dist-info/RECORD
